Metadata-Version: 1.1
Name: interactivemap
Version: 0.0.1
Summary: interactive world Map with zoom and selecting functions  
Home-page: UNKNOWN
Author: Fatih Seyrek <seyrek.f@googlemail.com>
Author-email: UNKNOWN
License: MIT
Platform: UNKNOWN
Classifier: Framework :: Dash
